wdocker.py
wdocker-0.2.0.data/scripts/wdocker
wdocker-0.2.0.dist-info/DESCRIPTION.rst
wdocker-0.2.0.dist-info/METADATA
wdocker-0.2.0.dist-info/RECORD
wdocker-0.2.0.dist-info/WHEEL
wdocker-0.2.0.dist-info/metadata.json
wdocker-0.2.0.dist-info/top_level.txt
