Metadata-Version: 2.0
Name: wdocker
Version: 0.2.0
Summary: Define docker commands in your Dockerfile
Home-page: http://github.com/babab/wdocker
Author: Benjamin Althues
Author-email: benjamin@babab.nl
License: ISC
Download-URL: https://pypi.python.org/pypi/wdocker
Platform: any
Classifier: Development Status :: 4 - Beta
Classifier: Environment :: Console
Classifier: Intended Audience :: Developers
Classifier: Intended Audience :: End Users/Desktop
Classifier: Intended Audience :: System Administrators
Classifier: License :: OSI Approved :: ISC License (ISCL)
Classifier: Natural Language :: English
Classifier: Operating System :: OS Independent
Classifier: Programming Language :: Python
Classifier: Programming Language :: Unix Shell
Classifier: Topic :: Scientific/Engineering :: Visualization
Classifier: Topic :: Software Development :: User Interfaces
Classifier: Topic :: System :: System Shells
Classifier: Topic :: Text Processing
Classifier: Topic :: Utilities
